awsmfunc/__init__.py
awsmfunc/base.py
awsmfunc/detect.py
awsmfunc/dovi.py
awsmfunc/legacy.py
awsmfunc/py.typed
awsmfunc/types/__init__.py
awsmfunc/types/dovi.py
awsmfunc/types/misc.py
awsmfunc/types/placebo.py
awsmfunc-1.3.4.dist-info/LICENSE
awsmfunc-1.3.4.dist-info/METADATA
awsmfunc-1.3.4.dist-info/WHEEL
awsmfunc-1.3.4.dist-info/top_level.txt
awsmfunc-1.3.4.dist-info/RECORD
