Metadata-Version: 2.1
Name: awsmfunc
Version: 1.3.4
Summary: awesome VapourSynth functions
Author: OpusGang
License: MIT
Project-URL: Homepage, https://github.com/OpusGang/awsmfunc
Requires-Python: >=3.9
License-File: LICENSE
Requires-Dist: VapourSynth (>=57)
Requires-Dist: numpy
Requires-Dist: vs-rekt (>=1.0.0)
Requires-Dist: vsutil (>=0.7.0)
Provides-Extra: dev
Requires-Dist: pylint ; extra == 'dev'
Requires-Dist: toml ; extra == 'dev'
Requires-Dist: yapf ; extra == 'dev'
